soe/__init__.py
soe/broker.py
soe/docs_index.py
soe/init.py
soe/types.py
soe/validation.py
soe_ai-0.1.0.dist-info/licenses/LICENSE
soe_ai-0.1.0.dist-info/METADATA
soe_ai-0.1.0.dist-info/WHEEL
soe_ai-0.1.0.dist-info/top_level.txt
soe_ai-0.1.0.dist-info/RECORD
