Metadata-Version: 2.4
Name: soe-ai
Version: 0.1.0
Summary: Signal-driven Orchestration Engine - Agent orchestration with event-driven workflow engine
Author-email: Pedro Garcia <pedro@example.com>
License-Expression: MIT
Project-URL: Homepage, https://github.com/pgarcia14180/soe
Project-URL: Documentation, https://github.com/pgarcia14180/soe/tree/master/docs
Project-URL: Repository, https://github.com/pgarcia14180/soe
Project-URL: Issues, https://github.com/pgarcia14180/soe/issues
Keywords: orchestration,agent,workflow,automation
Classifier: Development Status :: 3 - Alpha
Classifier: Intended Audience :: Developers
Classifier: Programming Language :: Python :: 3
Classifier: Programming Language :: Python :: 3.8
Classifier: Programming Language :: Python :: 3.9
Classifier: Programming Language :: Python :: 3.10
Classifier: Programming Language :: Python :: 3.11
Classifier: Programming Language :: Python :: 3.12
Requires-Python: >=3.8
License-File: LICENSE
Requires-Dist: pyyaml>=6.0
Requires-Dist: pydantic>=2.0.0
Requires-Dist: jinja2>=3.0.0
Provides-Extra: dev
Requires-Dist: pytest>=7.0; extra == "dev"
Requires-Dist: pytest-cov>=4.0; extra == "dev"
Requires-Dist: black>=23.0; extra == "dev"
Requires-Dist: mypy>=1.0; extra == "dev"
Requires-Dist: ruff>=0.1.0; extra == "dev"
Provides-Extra: integration
Requires-Dist: openai>=1.0.0; extra == "integration"
Requires-Dist: requests>=2.28.0; extra == "integration"
Dynamic: license-file
